{"ref":"8ba897fa-f210-413d-9853-b39edf16112e","content":"{\"version\":2,\"machineId\":\"5584e60f-ea08-4770-accc-2b4d536ae1a9\",\"content\":\"{\\\"linux\\\":\\\"[\\\\n    {\\\\n        \\\\\\\"key\\\\\\\": \\\\\\\"escape\\\\\\\",\\\\n        \\\\\\\"command\\\\\\\": \\\\\\\"macros.switchToEditorHidePanes\\\\\\\",\\\\n        \\\\\\\"when\\\\\\\": \\\\\\\"panelFocus || terminalFocus \\\\\\\"\\\\n    },\\\\n    {\\\\n        \\\\\\\"key\\\\\\\": \\\\\\\"escape\\\\\\\",\\\\n        \\\\\\\"command\\\\\\\": \\\\\\\"macros.switchToEditorHidePanes\\\\\\\",\\\\n        \\\\\\\"when\\\\\\\": \\\\\\\"editorIsOpen && sideBarVisible\\\\\\\"\\\\n    },\\\\n    {\\\\n        \\\\\\\"key\\\\\\\": \\\\\\\"escape\\\\\\\",\\\\n        \\\\\\\"command\\\\\\\": \\\\\\\"macros.switchToEditorHidePanes\\\\\\\",\\\\n        \\\\\\\"when\\\\\\\": \\\\\\\"activePanel\\\\\\\"\\\\n    },\\\\n{\\\\n    \\\\\\\"key\\\\\\\": \\\\\\\"ctrl+w\\\\\\\",\\\\n    \\\\\\\"command\\\\\\\": \\\\\\\"workbench.action.closeActiveEditor\\\\\\\"\\\\n}\\\\n]\\\"}\"}","platformSpecific":true}